{
  "formula_id": "6688bb9f2f7b",
  "deontic_formula": {
    "formula_id": "6688bb9f2f7b",
    "operator": "O",
    "proposition": "pay_contractor",
    "agent": {
      "identifier": "agent_3338",
      "name": "Contractor",
      "agent_type": "organization",
      "properties": {},
      "hash": "fd83345a"
    },
    "beneficiary": null,
    "conditions": [
      "30 days of completion"
    ],
    "temporal_conditions": [
      {
        "operator": "U",
        "condition": "30 days",
        "start_time": null,
        "end_time": "30 days",
        "duration": null
      }
    ],
    "legal_context": {
      "jurisdiction": "Illinois, USA",
      "legal_domain": "contract",
      "applicable_law": null,
      "precedents": [],
      "exceptions": []
    },
    "confidence": 0.95,
    "source_text": "The Client shall pay the Contractor within 30 days of completion",
    "variables": {},
    "quantifiers": [],
    "fol_string": "O[agent_3338](U((30 days of completion) \u2192 (pay_contractor)))",
    "creation_timestamp": "2025-08-31T19:10:24.758690"
  },
  "source_document_cid": "mock_doc_cid",
  "source_text_excerpt": "The Client shall pay the Contractor within 30 days of completion",
  "extraction_metadata": {
    "collection": "Springfield Construction Contract"
  },
  "translations": {},
  "translation_cids": {},
  "provenance_chain": null,
  "creation_timestamp": "2025-08-31T19:10:24.768613",
  "confidence_score": 0.95,
  "validation_results": {}
}